package/__init__.py
package/inference/__init__.py
package/inference/serving.py
package/inference/serving_app/__init__.py
package/inference/serving_app/application.py
package/inference/serving_app/exceptions.py
package/inference/serving_app/service/__init__.py
package/inference/serving_app/service/healthz.py
package/inference/serving_app/service/metrics.py
package/inference/serving_app/serving/__init__.py
package/inference/serving_app/serving/v1/__init__.py
package/inference/serving_app/serving/v1/views.py
package/inference/serving_app/serving/v2/__init__.py
package/inference/serving_app/serving/v2/views.py
package/inference/serving_app/settings.py
aicloud_deploy-0.0.1.dist-info/LICENSE
aicloud_deploy-0.0.1.dist-info/WHEEL
aicloud_deploy-0.0.1.dist-info/METADATA
aicloud_deploy-0.0.1.dist-info/RECORD
